collective.blueline-1.0b1-py2.7-nspkg.pth
collective/blueline/__init__.py
collective/blueline/config.py
collective/blueline/configure.zcml
collective/blueline/controlpanel.py
collective/blueline/interfaces.py
collective/blueline/profiles.zcml
collective/blueline/setuphandlers.py
collective/blueline/testing.py
collective/blueline/Extensions/Install.py
collective/blueline/Extensions/__init__.py
collective/blueline/browser/__init__.py
collective/blueline/browser/configure.zcml
collective/blueline/browser/viewlets.py
collective/blueline/browser/static/1428946240_line_width.png
collective/blueline/browser/static/blueline.png
collective/blueline/browser/static/icon.png
collective/blueline/browser/static/megaphone.png
collective/blueline/browser/static/megaphone_icon.png
collective/blueline/browser/templates/abovecontent.pt
collective/blueline/browser/templates/belowcontent.pt
collective/blueline/browser/templates/belowcontentbody.pt
collective/blueline/browser/templates/footer.pt
collective/blueline/browser/templates/header.pt
collective/blueline/browser/templates/htmlhead.pt
collective/blueline/locales/collective.blueline.pot
collective/blueline/locales/manual.pot
collective/blueline/locales/plone.pot
collective/blueline/locales/es/LC_MESSAGES/collective.blueline.po
collective/blueline/locales/es/LC_MESSAGES/plone.po
collective/blueline/locales/pt_BR/LC_MESSAGES/collective.blueline.po
collective/blueline/locales/pt_BR/LC_MESSAGES/plone.po
collective/blueline/portlets/__init__.py
collective/blueline/portlets/blueline.pt
collective/blueline/portlets/blueline.py
collective/blueline/portlets/configure.zcml
collective/blueline/profiles/default/browserlayer.xml
collective/blueline/profiles/default/controlpanel.xml
collective/blueline/profiles/default/metadata.xml
collective/blueline/profiles/default/portlets.xml
collective/blueline/profiles/default/registry.xml
collective/blueline/profiles/default/viewlets.xml
collective.blueline-1.0b1.dist-info/DESCRIPTION.rst
collective.blueline-1.0b1.dist-info/METADATA
collective.blueline-1.0b1.dist-info/RECORD
collective.blueline-1.0b1.dist-info/WHEEL
collective.blueline-1.0b1.dist-info/entry_points.txt
collective.blueline-1.0b1.dist-info/metadata.json
collective.blueline-1.0b1.dist-info/namespace_packages.txt
collective.blueline-1.0b1.dist-info/top_level.txt
