Metadata-Version: 2.0
Name: collective.blueline
Version: 1.0b1
Summary: Helper viewlets to easily insert code on the layout of a Plone site.
Home-page: https://github.com/simplesconsultoria/collective.blueline
Author: Simples Consultoria
Author-email: products@simplesconsultoria.com.br
License: UNKNOWN
Platform: UNKNOWN
Classifier: Development Status :: 3 - Alpha
Classifier: Environment :: Web Environment
Classifier: Framework :: Plone
Classifier: Framework :: Plone :: 4.3
Classifier: Framework :: Plone :: 5.0
Classifier: Intended Audience :: System Administrators
Classifier: License :: OSI Approved :: GNU General Public License v2 (GPLv2)
Classifier: Operating System :: OS Independent
Classifier: Programming Language :: Python
Classifier: Programming Language :: Python :: 2.7
Classifier: Topic :: Software Development :: Libraries :: Python Modules
Requires-Dist: Products.CMFCore
Requires-Dist: Products.CMFPlone (>=4.3)
Requires-Dist: Products.GenericSetup
Requires-Dist: lxml
Requires-Dist: plone.api
Requires-Dist: plone.app.layout
Requires-Dist: plone.app.portlets
Requires-Dist: plone.app.registry
Requires-Dist: plone.autoform
Requires-Dist: plone.portlets
Requires-Dist: plone.supermodel
Requires-Dist: setuptools
Requires-Dist: zope.formlib
Requires-Dist: zope.i18nmessageid
Requires-Dist: zope.interface
Requires-Dist: zope.schema
Provides-Extra: test
Requires-Dist: AccessControl; extra == 'test'
Requires-Dist: plone.app.robotframework; extra == 'test'
Requires-Dist: plone.app.testing[robot]; extra == 'test'
Requires-Dist: plone.browserlayer; extra == 'test'
Requires-Dist: plone.registry; extra == 'test'
Requires-Dist: plone.testing; extra == 'test'
Requires-Dist: robotsuite; extra == 'test'
Requires-Dist: zope.component; extra == 'test'
